simplug.py
simplug-0.5.6.dist-info/LICENSE
simplug-0.5.6.dist-info/METADATA
simplug-0.5.6.dist-info/WHEEL
simplug-0.5.6.dist-info/RECORD
