Metadata-Version: 2.3
Name: simplug
Version: 0.5.6
Summary: A simple plugin system for python with async hooks supported
License: MIT
Author: pwwang
Author-email: pwwang@pwwang.com
Requires-Python: >=3.9,<4.0
Classifier: License :: OSI Approved :: MIT License
Classifier: Programming Language :: Python :: 3
Classifier: Programming Language :: Python :: 3.9
Classifier: Programming Language :: Python :: 3.10
Classifier: Programming Language :: Python :: 3.11
Classifier: Programming Language :: Python :: 3.12
Classifier: Programming Language :: Python :: 3.13
Requires-Dist: diot (>=0.3,<0.4)
Project-URL: Homepage, https://github.com/pwwang/simplug
Project-URL: Repository, https://github.com/pwwang/simplug
